<?xml version="1.0" encoding="utf-8" ?><dwsync><file name="cv.html" server="ftp.nickvolkert.com/art/" local="3419707383" remote="12009634772" Dst="-1" /><file name="favicon.ico" server="ftp.nickvolkert.com/art/" local="3318379800" remote="12009634772" Dst="-1" /><file name="index.html" server="ftp.nickvolkert.com/art/" local="3419707383" remote="12009635072" Dst="-1" /><file name="index_0209.html" server="ftp.nickvolkert.com/art/" local="3318379980" remote="12009635072" Dst="-1" /><file name="links.html" server="ftp.nickvolkert.com/art/" local="3419707383" remote="12009635072" Dst="-1" /><file name="pricing.html" server="ftp.nickvolkert.com/art/" local="3419707383" remote="12009635072" Dst="-1" /><file name="cv.html" server="ftp.nickvolkert.com" local="3419707383" remote="12025437872" Dst="-1" /><file name="favicon.ico" server="ftp.nickvolkert.com" local="3318379800" remote="12025437872" Dst="-1" /><file name="index.html" server="ftp.nickvolkert.com" local="3419707383" remote="12025437932" Dst="-1" /><file name="index_0209.html" server="ftp.nickvolkert.com" local="3318379980" remote="12025437932" Dst="-1" /><file name="links.html" server="ftp.nickvolkert.com" local="3419707383" remote="12025437932" Dst="-1" /><file name="pricing.html" server="ftp.nickvolkert.com" local="3419707383" remote="12025437992" Dst="-1" /><file name="cv.html" server="ftp.nickvolkert.com//art/" local="3578092042" remote="3578081220" Dst="-1" /><file name="favicon.ico" server="ftp.nickvolkert.com//art/" local="3318379800" remote="3566223120" Dst="-1" /><file name="index.html" server="ftp.nickvolkert.com//art/" local="3578092042" remote="3578081220" Dst="-1" /><file name="index_0209.html" server="ftp.nickvolkert.com//art/" local="3472929393" remote="3566223180" Dst="-1" /><file name="links.html" server="ftp.nickvolkert.com//art/" local="3578092042" remote="3578081220" Dst="-1" /><file name="pricing.html" server="ftp.nickvolkert.com//art/" local="3578092042" remote="3578081280" Dst="-1" /><file name="shows.html" server="ftp.nickvolkert.com//art/" local="3578092042" remote="3578081280" Dst="-1" /><file name="artiststatement.html" server="ftp.nickvolkert.com//art/" local="3578092042" remote="3578081220" Dst="-1" /><file name="commission.html" server="ftp.nickvolkert.com//art/" local="3578092042" remote="3578081220" Dst="-1" /><file name="contact.html" server="ftp.nickvolkert.com//art/" local="3578092042" remote="3578081220" Dst="-1" /><file name="home_0209.html" server="ftp.nickvolkert.com//art/" local="3578092042" remote="3578081220" Dst="-1" /><file name="home.html" server="ftp.nickvolkert.com//art/" local="3578092042" remote="3578081220" Dst="-1" /></dwsync>