<?xml version="1.0" encoding="utf-8" ?><dwsync><file name="1-ie.png" server="ftp.nickvolkert.com/thursdaytreat/" local="3338237340" remote="12009635912" Dst="-1" /><file name="1.png" server="ftp.nickvolkert.com/thursdaytreat/" local="3338237340" remote="12009635912" Dst="-1" /><file name="2-ie.png" server="ftp.nickvolkert.com/thursdaytreat/" local="3338237340" remote="12009635912" Dst="-1" /><file name="2.png" server="ftp.nickvolkert.com/thursdaytreat/" local="3338237340" remote="12009635912" Dst="-1" /><file name="3-ie.png" server="ftp.nickvolkert.com/thursdaytreat/" local="3338237340" remote="12009635912" Dst="-1" /><file name="3.png" server="ftp.nickvolkert.com/thursdaytreat/" local="3338237340" remote="12009635912" Dst="-1" /><file name="4-ie.png" server="ftp.nickvolkert.com/thursdaytreat/" local="3338237340" remote="12009635972" Dst="-1" /><file name="4.png" server="ftp.nickvolkert.com/thursdaytreat/" local="3338237340" remote="12009635972" Dst="-1" /><file name="header-ie.png" server="ftp.nickvolkert.com/thursdaytreat/" local="3338237340" remote="12009635972" Dst="-1" /><file name="header.png" server="ftp.nickvolkert.com/thursdaytreat/" local="3338237340" remote="12009635972" Dst="-1" /><file name="pirate_promo.gif" server="ftp.nickvolkert.com/thursdaytreat/" local="3338237340" remote="12009635972" Dst="-1" /><file name="victor_bg.gif" server="ftp.nickvolkert.com/thursdaytreat/" local="3338237340" remote="12009635972" Dst="-1" /><file name="1-ie.png" server="ftp.nickvolkert.com" local="3338237340" remote="12025440212" Dst="-1" /><file name="1.png" server="ftp.nickvolkert.com" local="3338237340" remote="12025440212" Dst="-1" /><file name="2-ie.png" server="ftp.nickvolkert.com" local="3338237340" remote="12025440212" Dst="-1" /><file name="2.png" server="ftp.nickvolkert.com" local="3338237340" remote="12025440212" Dst="-1" /><file name="3-ie.png" server="ftp.nickvolkert.com" local="3338237340" remote="12025440212" Dst="-1" /><file name="3.png" server="ftp.nickvolkert.com" local="3338237340" remote="12025440212" Dst="-1" /><file name="4-ie.png" server="ftp.nickvolkert.com" local="3338237340" remote="12025440212" Dst="-1" /><file name="4.png" server="ftp.nickvolkert.com" local="3338237340" remote="12025440212" Dst="-1" /><file name="header-ie.png" server="ftp.nickvolkert.com" local="3338237340" remote="12025440212" Dst="-1" /><file name="header.png" server="ftp.nickvolkert.com" local="3338237340" remote="12025440212" Dst="-1" /><file name="pirate_promo.gif" server="ftp.nickvolkert.com" local="3338237340" remote="12025440212" Dst="-1" /><file name="victor_bg.gif" server="ftp.nickvolkert.com" local="3338237340" remote="12025440212" Dst="-1" /><file name="1-ie.png" server="ftp.nickvolkert.com//thursdaytreat/" local="3338237340" remote="7767896956" Dst="-1" /><file name="2-ie.png" server="ftp.nickvolkert.com//thursdaytreat/" local="3338237340" remote="-4611698831136869508" Dst="-1" /><file name="1.png" server="ftp.nickvolkert.com//thursdaytreat/" local="3338237340" remote="-4611698831136869508" Dst="-1" /><file name="3-ie.png" server="ftp.nickvolkert.com//thursdaytreat/" local="3338237340" remote="-4611698831136869508" Dst="-1" /><file name="2.png" server="ftp.nickvolkert.com//thursdaytreat/" local="3338237340" remote="-4611698831136869508" Dst="-1" /><file name="4-ie.png" server="ftp.nickvolkert.com//thursdaytreat/" local="3338237340" remote="-4611698831136869508" Dst="-1" /><file name="3.png" server="ftp.nickvolkert.com//thursdaytreat/" local="3338237340" remote="-4611698831136869508" Dst="-1" /><file name="header-ie.png" server="ftp.nickvolkert.com//thursdaytreat/" local="3338237340" remote="-4611698831136869508" Dst="-1" /><file name="4.png" server="ftp.nickvolkert.com//thursdaytreat/" local="3338237340" remote="-4611698831136869508" Dst="-1" /><file name="pirate_promo.gif" server="ftp.nickvolkert.com//thursdaytreat/" local="3338237340" remote="-4611698831136869508" Dst="-1" /><file name="victor_bg.gif" server="ftp.nickvolkert.com//thursdaytreat/" local="3338237340" remote="-4611698831136869508" Dst="-1" /><file name="header.png" server="ftp.nickvolkert.com//thursdaytreat/" local="3338237340" remote="-4611698831136869508" Dst="-1" /></dwsync>